[
  {"marka": "Algida", "durum": "boykot", "logo": ""},
  {"marka": "Burger King", "durum": "boykot", "logo": ""},
  {"marka": "Carrefour", "durum": "boykot", "logo": ""},
  {"marka": "Cheetos", "durum": "boykot", "logo": ""},
  {"marka": "Calve", "durum": "boykot", "logo": ""},
  {"marka": "Danone", "durum": "boykot", "logo": ""},
  {"marka": "Doritos", "durum": "boykot", "logo": ""},
  {"marka": "Dominos", "durum": "boykot", "logo": ""},
  {"marka": "Hellman's", "durum": "boykot", "logo": ""},
  {"marka": "Knorr", "durum": "boykot", "logo": ""},
  {"marka": "KFC", "durum": "boykot", "logo": ""},
  {"marka": "KitKat", "durum": "boykot", "logo": ""},
  {"marka": "Lay's", "durum": "boykot", "logo": ""},
  {"marka": "McDonald's", "durum": "boykot", "logo": ""},
  {"marka": "Mondelez", "durum": "boykot", "logo": ""},
  {"marka": "Nestle", "durum": "boykot", "logo": ""},
  {"marka": "Nesquik", "durum": "boykot", "logo": ""},
  {"marka": "Popeyes", "durum": "boykot", "logo": ""},
  {"marka": "Pizza Hut", "durum": "boykot", "logo": ""},
  {"marka": "Papa John's", "durum": "boykot", "logo": ""},
  {"marka": "Perrier", "durum": "boykot", "logo": ""},
  {"marka": "Procter & Gamble", "durum": "boykot", "logo": ""},
  {"marka": "Coca-Cola", "durum": "boykot", "logo": ""},
  {"marka": "Coffee Mate", "durum": "boykot", "logo": ""},
  {"marka": "Fanta", "durum": "boykot", "logo": ""},
  {"marka": "Lipton", "durum": "boykot", "logo": ""},
  {"marka": "Mountain Dew", "durum": "boykot", "logo": ""},
  {"marka": "Nestle Pure Life", "durum": "boykot", "logo": ""},
  {"marka": "Nescafe", "durum": "boykot", "logo": ""},
  {"marka": "Pepsi", "durum": "boykot", "logo": ""},
  {"marka": "7up", "durum": "boykot", "logo": ""},
  {"marka": "Starbucks", "durum": "boykot", "logo": ""},
  {"marka": "SodaStream", "durum": "boykot", "logo": ""},
  {"marka": "Schweppes", "durum": "boykot", "logo": ""},
  {"marka": "Sprite", "durum": "boykot", "logo": ""},
  {"marka": "Tropicana", "durum": "boykot", "logo": ""},
  {"marka": "Unilever", "durum": "boykot", "logo": ""},
  {"marka": "Axe", "durum": "boykot", "logo": ""},
  {"marka": "Cerave", "durum": "boykot", "logo": ""},
  {"marka": "Chanel", "durum": "boykot", "logo": ""},
  {"marka": "Dove", "durum": "boykot", "logo": ""},
  {"marka": "Garnier", "durum": "boykot", "logo": ""},
  {"marka": "L’Oreal Paris", "durum": "boykot", "logo": ""},
  {"marka": "La Roche-Posay", "durum": "boykot", "logo": ""},
  {"marka": "Lux", "durum": "boykot", "logo": ""},
  {"marka": "Maybelline New York", "durum": "boykot", "logo": ""},
  {"marka": "MAC", "durum": "boykot", "logo": ""},
  {"marka": "Maybelline", "durum": "boykot", "logo": ""},
  {"marka": "Simple", "durum": "boykot", "logo": ""},
  {"marka": "Yves Saint Laurent Beauty", "durum": "boykot", "logo": ""},
  {"marka": "Always", "durum": "boykot", "logo": ""},
  {"marka": "ALO Deterjan", "durum": "boykot", "logo": ""},
  {"marka": "Ariel", "durum": "boykot", "logo": ""},
  {"marka": "Braun", "durum": "boykot", "logo": ""},
  {"marka": "Cif", "durum": "boykot", "logo": ""},
  {"marka": "Domestos", "durum": "boykot", "logo": ""},
  {"marka": "Fairy", "durum": "boykot", "logo": ""},
  {"marka": "Gillette", "durum": "boykot", "logo": ""},
  {"marka": "Head and Shoulders", "durum": "boykot", "logo": ""},
  {"marka": "Henkel", "durum": "boykot", "logo": ""},
  {"marka": "İpana", "durum": "boykot", "logo": ""},
  {"marka": "Orkid", "durum": "boykot", "logo": ""},
  {"marka": "Omo", "durum": "boykot", "logo": ""},
  {"marka": "Oral B", "durum": "boykot", "logo": ""},
  {"marka": "Rexona", "durum": "boykot", "logo": ""},
  {"marka": "Pampers", "durum": "boykot", "logo": ""},
  {"marka": "Prima", "durum": "boykot", "logo": ""},
  {"marka": "Pantene", "durum": "boykot", "logo": ""},
  {"marka": "Signal", "durum": "boykot", "logo": ""},
  {"marka": "Sudocrem", "durum": "boykot", "logo": ""},
  {"marka": "Vicks", "durum": "boykot", "logo": ""},
  {"marka": "AXA", "durum": "boykot", "logo": ""},
  {"marka": "Amazon", "durum": "boykot", "logo": ""},
  {"marka": "Airbnb", "durum": "boykot", "logo": ""},
  {"marka": "Dell", "durum": "boykot", "logo": ""},
  {"marka": "Disney", "durum": "boykot", "logo": ""},
  {"marka": "Fiverr", "durum": "boykot", "logo": ""},
  {"marka": "HP (Hewlett Packard)", "durum": "boykot", "logo": ""},
  {"marka": "Siemens", "durum": "boykot", "logo": ""},
  {"marka": "Wix", "durum": "boykot", "logo": ""},
  {"marka": "CAT", "durum": "boykot", "logo": ""},
  {"marka": "Diesel", "durum": "boykot", "logo": ""},
  {"marka": "Giorgio Armani Beauty", "durum": "boykot", "logo": ""},
  {"marka": "Louis Vuitton", "durum": "boykot", "logo": ""},
  {"marka": "Marks and Spencer", "durum": "boykot", "logo": ""},
  {"marka": "M&S", "durum": "boykot", "logo": ""},
  {"marka": "Puma", "durum": "boykot", "logo": ""},
  {"marka": "Ralph Lauren Frangrances", "durum": "boykot", "logo": ""},
  {"marka": "Skechers", "durum": "boykot", "logo": ""},
  {"marka": "Victorias Secret", "durum": "boykot", "logo": ""},
  {"marka": "Bayer", "durum": "boykot", "logo": ""},
  {"marka": "Pfizer", "durum": "boykot", "logo": ""},
  {"marka": "Hyundai", "durum": "boykot", "logo": ""},
  {"marka": "HSBC", "durum": "boykot", "logo": ""},
  {"marka": "BP Petrol", "durum": "boykot", "logo": ""},
  {"marka": "Papara", "durum": "boykot", "logo": "https://www.papara.com/papara_icon.png"}
]
